Metadata-Version: 1.2
Name: deepmatcher
Version: 0.1.2.post2
Summary: A deep learning package for entity matching
Home-page: http://deepmatcher.ml
Author: Sidharth Mudgal, Han Li
Author-email: uwmagellan@gmail.com
License: BSD
Platform: UNKNOWN
Requires-Python: >=3.5
